setup.py
kast1/__init__.py
kast1/asgi.py
kast1/settings.py
kast1/urls.py
kast1/wsgi.py
kast1.egg-info/PKG-INFO
kast1.egg-info/SOURCES.txt
kast1.egg-info/dependency_links.txt
kast1.egg-info/requires.txt
kast1.egg-info/top_level.txt
st1/__init__.py
st1/admin.py
st1/apps.py
st1/fields.py
st1/forms.py
st1/models.py
st1/states.py
st1/tests.py
st1/views.py
st1/migrations/__init__.py